LICENSE
MANIFEST.in
README.rst
setup.cfg
setup.py
jmespath/__init__.py
jmespath/ast.py
jmespath/compat.py
jmespath/exceptions.py
jmespath/functions.py
jmespath/lexer.py
jmespath/parser.py
jmespath/visitor.py
qcloudcli/Qcloudcli.py
qcloudcli/__init__.py
qcloudcli/autoComplete.py
qcloudcli/commandConfigure.py
qcloudcli/completer.py
qcloudcli/configure.py
qcloudcli/handleCmd.py
qcloudcli/handleData.py
qcloudcli/handleParameter.py
qcloudcli/result.py
qcloudcli/shellcomplete.sh
qcloudcli/showHelp.py
qcloudcli/six.py
qcloudcli/table.py
qcloudcli/text.py
qcloudcli.egg-info/PKG-INFO
qcloudcli.egg-info/SOURCES.txt
qcloudcli.egg-info/dependency_links.txt
qcloudcli.egg-info/entry_points.txt
qcloudcli.egg-info/top_level.txt
qcloudcli/advance/__init__.py
qcloudcli/advance/userConfigHandler.py
qcloudcli/advance/userProfileHandler.py
qcloudcli/colorama/__init__.py
qcloudcli/colorama/ansi.py
qcloudcli/colorama/ansitowin32.py
qcloudcli/colorama/initialise.py
qcloudcli/colorama/win32.py
qcloudcli/colorama/winterm.py
qcloudsdkaccount/AddProjectRequest.py
qcloudsdkaccount/DescribeProjectByOpenIDRequest.py
qcloudsdkaccount/DescribeProjectRequest.py
qcloudsdkaccount/DescribeUserGroupRequest.py
qcloudsdkaccount/UpdateProjectRequest.py
qcloudsdkaccount/__init__.py
qcloudsdkapigateway/BindEnvironmentRequest.py
qcloudsdkapigateway/BindSecretIdsRequest.py
qcloudsdkapigateway/BindSubDomainRequest.py
qcloudsdkapigateway/CreateApiKeyRequest.py
qcloudsdkapigateway/CreateApiRequest.py
qcloudsdkapigateway/CreateServiceRequest.py
qcloudsdkapigateway/CreateUsagePlanRequest.py
qcloudsdkapigateway/DeleteApiKeyRequest.py
qcloudsdkapigateway/DeleteApiRequest.py
qcloudsdkapigateway/DeleteServiceSubDomainMappingRequest.py
qcloudsdkapigateway/DeleteUsagePlanRequest.py
qcloudsdkapigateway/DescribeApiKeysStatusRequest.py
qcloudsdkapigateway/DescribeApiRequest.py
qcloudsdkapigateway/DescribeApisStatusRequest.py
qcloudsdkapigateway/DescribeServiceEnvironmentReleaseHistoryRequest.py
qcloudsdkapigateway/DescribeServiceReleaseVersionRequest.py
qcloudsdkapigateway/DescribeServiceRequest.py
qcloudsdkapigateway/DescribeServiceSubDomainMappingsRequest.py
