Metadata-Version: 1.1
Name: qcloudcli
Version: 1.9.20
Summary: Universal Command Line Environment for qcloud
Home-page: https://github.com/QcloudApi/qcloudcli.git
Author: Qcloud
Author-email: QcloudApi@tencent.com
License: UNKNOWN
Platform: unix
Platform: linux
Platform: win64
Classifier: Development Status :: 5 - Production/Stable
Classifier: Intended Audience :: Developers
Classifier: License :: OSI Approved :: Apache Software License
Classifier: Programming Language :: Python
Classifier: Programming Language :: Python :: 2.6
Classifier: Programming Language :: Python :: 2.7
Classifier: Programming Language :: Python :: 3
Classifier: Programming Language :: Python :: 3.1
Classifier: Programming Language :: Python :: 3.2
Classifier: Programming Language :: Python :: 3.3
Classifier: Programming Language :: Python :: 3.4
Classifier: Programming Language :: Python :: 3.5
Classifier: Programming Language :: Python :: 3.6
